merch_scripts_package/__init__.py
merch_scripts_package-99.0.1.dist-info/METADATA
merch_scripts_package-99.0.1.dist-info/WHEEL
merch_scripts_package-99.0.1.dist-info/top_level.txt
merch_scripts_package-99.0.1.dist-info/RECORD
