Metadata-Version: 2.4
Name: merch_scripts_package
Version: 99.0.1
Summary: This package name is reserved to prevent dependency confusion attacks. Do not install.
Author-email: Jack Bouvier <jbouvier@woolworths.com.au>
Classifier: Programming Language :: Python :: 3
Classifier: License :: OSI Approved :: MIT License
Classifier: Operating System :: OS Independent
Requires-Python: >=3.7
